{
  "tags": [
    {
      "name": "release",
      "version": "0.17.876",
      "commit": "825e412",
      "upstream": "Releases",
      "lastUpdated": "2021-04-12T07:21:40.830Z"
    },
    {
      "name": "testing",
      "version": "0.17.876",
      "commit": "e24726b",
      "upstream": "Pre-releases",
      "lastUpdated": "2021-04-12T07:21:36.181Z"
    },
    {
      "name": "nightly",
      "version": "",
      "commit": "",
      "upstream": "",
      "lastUpdated": ""
    }
  ],
  "pulls": 16283388,
  "stars": 10
}
